jinja_excel_template/ExcelGenerator.py
jinja_excel_template/ExcelXMLMerger.py
jinja_excel_template/JinjaExcelEngine.py
jinja_excel_template/__init__.py
jinja_excel_template/cell_type/AreaChart.py
jinja_excel_template/cell_type/AreaChart3D.py
jinja_excel_template/cell_type/BarChart.py
jinja_excel_template/cell_type/BarChart3D.py
jinja_excel_template/cell_type/Chart.py
jinja_excel_template/cell_type/DateTime.py
jinja_excel_template/cell_type/General.py
jinja_excel_template/cell_type/Img.py
jinja_excel_template/cell_type/Number.py
jinja_excel_template/cell_type/PieChart.py
jinja_excel_template/cell_type/PieChart3D.py
jinja_excel_template/helper/DimensionHelper.py
jinja_excel_template/helper/GetAlignment.py
jinja_excel_template/helper/GetBorder.py
jinja_excel_template/helper/GetFill.py
jinja_excel_template/helper/GetFont.py
jinja_excel_template/helper/MergeCell.py
jinja_excel_template/helper/setCellStyle.py
jinja_excel_template/helper/setSheetAttr.py
jinja_excel_template/helper/setxmlattr.py
jinja_excel_template/helper/typeconverter.py
jinja_excel_template/helper/utils.py
jinja_excel_template-1.0.4.dist-info/LICENSE
jinja_excel_template-1.0.4.dist-info/METADATA
jinja_excel_template-1.0.4.dist-info/WHEEL
jinja_excel_template-1.0.4.dist-info/RECORD
