Metadata-Version: 2.1
Name: jinja-excel-template
Version: 1.0.4
Summary: Jinja based Excel Template support multiple sheets
Home-page: https://github.com/hkalex/jinja-excel-template
License: MIT
Keywords: jinja,excel,template,engine,xlsx,multi-sheet,multiple sheets,dynamic sheets
Author: AlexYeung
Author-email: hkalex@gmail.com
Requires-Python: >=3.10,<4.0
Classifier: License :: OSI Approved :: MIT License
Classifier: Programming Language :: Python :: 3
Classifier: Programming Language :: Python :: 3.10
Classifier: Programming Language :: Python :: 3.11
Requires-Dist: coverage (>=7.3.1,<8.0.0)
Requires-Dist: dateutils (>=0.6.12,<0.7.0)
Requires-Dist: jinja2 (>=3.1.2,<4.0.0)
Requires-Dist: lxml (>=4.9.3,<5.0.0)
Requires-Dist: openpyxl (>=3.1.2,<4.0.0)
Requires-Dist: pillow (>=10.0.1,<11.0.0)
Requires-Dist: pytest (>=7.4.2,<8.0.0)
Requires-Dist: pytest-cov (>=4.1.0,<5.0.0)
Project-URL: Repository, https://github.com/hkalex/jinja-excel-template
